MANIFEST.in
requirements-dev.txt
requirements.txt
setup.py
AmiBaker.egg-info/SOURCES.txt
amibaker/__init__.py
amibaker/__main__.py
amibaker/ami_baker.py
amibaker/ami_ec2.py
amibaker/main.py
amibaker/provisioner.py
amibaker/recipe.py
amibaker/util.py
amibaker/version.py
amibaker.egg-info/PKG-INFO
amibaker.egg-info/SOURCES.txt
amibaker.egg-info/dependency_links.txt
amibaker.egg-info/entry_points.txt
amibaker.egg-info/not-zip-safe
amibaker.egg-info/requires.txt
amibaker.egg-info/top_level.txt