Metadata-Version: 1.1
Name: amibaker
Version: 0.8.2
Summary: Automate creation of AWS AMIs.
Home-page: http://github.com/hamidnazari/amibaker
Author: Hamid Nazari
Author-email: hn@linux.com
License: MIT
Keywords: aws,amazon web services,ami,amazon machine images,automation
Platform: UNKNOWN
Classifier: Programming Language :: Python
Classifier: Programming Language :: Python :: 2.6
Classifier: Programming Language :: Python :: 2.7
Classifier: Intended Audience :: Developers
Classifier: License :: OSI Approved :: MIT License
Classifier: Operating System :: OS Independent
Classifier: Topic :: Software Development
Classifier: Topic :: Software Development :: Libraries
Classifier: Topic :: Software Development :: Libraries :: Python Modules
Classifier: Development Status :: 4 - Beta
